{
    "code":0,
    "error":0,
    "data":[
        {"id": "1", "name": "addProject","title":"新建项目" ,"type":"formlist"}, 
        {"id": "2", "name": "addProjectGather","title":"新建项目集" ,"type":"formlist"},
        {"id": "3", "name": "addTeacher","title":"新建讲师" ,"type":"formlist"},
        {"id": "5", "name": "editProject","title":"编辑项目" ,"type":"formlist"},
        {"id": "6", "name": "addProjectAddress","title":"新增培训地点" ,"type":"formlist"},
        {"id": "8", "name": "projectCard","title":"项目列表中的card","type":"cards"},
        {"id": "9", "name": "travelExpensesGroup","title":"差旅安排","type":"group"},
        {"id": "10", "name": "teacherCardGroup","title":"讲师安排","type":"group"},
        {"id": "11", "name": "teacherAddForm","title":"添加讲师安排" ,"type":"formlist"},
        {"id": "12", "name": "teacherSelectFrom","title":"讲师安排展示" ,"type":"formlist"},
        {"id": "13", "name": "teacherAddForm","title":"讲师安排修改" ,"type":"formlist"},
        {"id": "7", "name": "implementArrage","title":"实施安排","type":"group"},
        {"id": "14", "name": "implementAddFrom","title":"实施安排新增" ,"type":"formlist"},
        {"id": "15", "name": "implementSelectFrom","title":"实施安排展示" ,"type":"formlist"},
        {"id": "16", "name": "implementAddFrom","title":"实施安排修改" ,"type":"formlist"},
        {"id": "17", "name": "venueAddFrom","title":"添加会场安排" ,"type":"formlist"},
        {"id": "18", "name": "venueSelectFrom","title":"会场安排展示" ,"type":"formlist"},
        {"id": "19", "name": "venueAddFrom","title":"会场安排修改" ,"type":"formlist"},
        {"id": "20", "name": "longTravelAddFrom","title":"添加长途交通费" ,"type":"formlist"},
        {"id": "21", "name": "longTravelSelectFrom","title":"长途交通费展示" ,"type":"formlist"},
        {"id": "22", "name": "longTravelAddFrom","title":"长途交通费修改" ,"type":"formlist"},
        {"id": "23", "name": "shortTravelAddFrom","title":"添加市内交通费" ,"type":"formlist"},
        {"id": "24", "name": "shortTravelSelectFrom","title":"市内交通费展示" ,"type":"formlist"},
        {"id": "25", "name": "shortTravelAddFrom","title":"市内交通费修改" ,"type":"formlist"},
        {"id": "26", "name": "hotelTravelAddFrom","title":"添加住宿费" ,"type":"formlist"},
        {"id": "27", "name": "hotelTravelSelectFrom","title":"住宿费展示" ,"type":"formlist"},
        {"id": "28", "name": "hotelTravelAddFrom","title":"住宿费修改" ,"type":"formlist"},
        {"id": "29", "name": "mealTravelAddFrom","title":"添加餐费" ,"type":"formlist"},
        {"id": "30", "name": "mealTravelSelectFrom","title":"餐费展示" ,"type":"formlist"},
        {"id": "31", "name": "mealTravelAddFrom","title":"餐费修改" ,"type":"formlist"}
            ],
    "during_time":27,
    "end_time":1539500978642,
    "msg":"查询成功",
    "stat_time":1539500978615
    }